{"defaultCharacters":[

	{ "name":"あざみ", "sex":"female" },
	{ "name":"あじさい", "sex":"female" },
	{ "name":"あんず", "sex":"female" },
	{ "name":"うめ", "sex":"female" },
	{ "name":"えびね", "sex":"female" },
	{ "name":"かりん", "sex":"female" },
	{ "name":"きく", "sex":"female" },
	{ "name":"くらら", "sex":"female" },
	{ "name":"さくら", "sex":"female" },
	{ "name":"さざんか", "sex":"female" },
	{ "name":"じゃのめエリカ", "sex":"female" },
	{ "name":"すずらん", "sex":"female" },
	{ "name":"すみれ", "sex":"female" },
	{ "name":"ちんちょうか", "sex":"female" },
	{ "name":"つつじ", "sex":"female" },
	{ "name":"つばき", "sex":"female" },
	{ "name":"どくだみ", "sex":"female" },
	{ "name":"ぬばたま", "sex":"female" },
	{ "name":"のぎく", "sex":"female" },
	{ "name":"はるじおん", "sex":"female" },
	{ "name":"はるりんどう", "sex":"female" },
	{ "name":"ばら", "sex":"female" },
	{ "name":"ばれいしょ", "sex":"female" },
	{ "name":"ひなぎく", "sex":"female" },
	{ "name":"ひまわり", "sex":"female" },
	{ "name":"ひめざくろ", "sex":"female" },
	{ "name":"ひめじょおん", "sex":"female" },
	{ "name":"ひめりんご", "sex":"female" },
	{ "name":"へびいちご", "sex":"female" },
	{ "name":"むらさきごてん", "sex":"female" },
	{ "name":"もも", "sex":"female" },
	{ "name":"ゆり", "sex":"female" },
	{ "name":"アイリス", "sex":"female" },
	{ "name":"アキレア", "sex":"female" },
	{ "name":"アサガオ", "sex":"female" },
	{ "name":"アジサイ", "sex":"female" },
	{ "name":"アツモリソウ", "sex":"female" },
	{ "name":"アネモネ", "sex":"female" },
	{ "name":"アブラナ", "sex":"female" },
	{ "name":"アマリリス", "sex":"female" },
	{ "name":"アヤメ", "sex":"female" },
	{ "name":"アルストロメリア", "sex":"female" },
	{ "name":"アロエ", "sex":"female" },
	{ "name":"イチゴ", "sex":"female" },
	{ "name":"イブキトラノオ", "sex":"female" },
	{ "name":"ウメ", "sex":"female" },
	{ "name":"エゾエンゴサク", "sex":"female" },
	{ "name":"エゾヤマザクラ", "sex":"female" },
	{ "name":"エゾルリムラサキ", "sex":"female" },
	{ "name":"オオイヌノフグリ", "sex":"female" },
	{ "name":"オオガハス", "sex":"female" },
	{ "name":"オオハンゴンソウ", "sex":"female" },
	{ "name":"オオバコ", "sex":"female" },
	{ "name":"オトギリソウ", "sex":"female" },
	{ "name":"オトメユリ", "sex":"female" },
	{ "name":"オンシジウム", "sex":"female" },
	{ "name":"カキ", "sex":"female" },
	{ "name":"カキツバタ", "sex":"female" },
	{ "name":"カサブランカ", "sex":"female" },
	{ "name":"カタクリ", "sex":"female" },
	{ "name":"カトレア", "sex":"female" },
	{ "name":"カノコユリ", "sex":"female" },
	{ "name":"カボチャ", "sex":"female" },
	{ "name":"カラスノエンドウ", "sex":"female" },
	{ "name":"カーネーション", "sex":"female" },
	{ "name":"ガーベラ", "sex":"female" },
	{ "name":"キキョウ", "sex":"female" },
	{ "name":"キク", "sex":"female" },
	{ "name":"キタコブシ", "sex":"female" },
	{ "name":"キュウリ", "sex":"female" },
	{ "name":"キョウチクトウ", "sex":"female" },
	{ "name":"キリ", "sex":"female" },
	{ "name":"キンシバイ", "sex":"female" },
	{ "name":"キンセンカ", "sex":"female" },
	{ "name":"キンモクセイ", "sex":"female" },
	{ "name":"クズ", "sex":"female" },
	{ "name":"クマガイソウ", "sex":"female" },
	{ "name":"クリ", "sex":"female" },
	{ "name":"クレマチス", "sex":"female" },
	{ "name":"クロッカス", "sex":"female" },
	{ "name":"クロユリ", "sex":"female" },
	{ "name":"グラジオラス", "sex":"female" },
	{ "name":"ケイトウ", "sex":"female" },
	{ "name":"ゲッカコウ", "sex":"female" },
	{ "name":"コウリンタンポポ", "sex":"female" },
	{ "name":"コケモモ", "sex":"female" },
	{ "name":"コスモス", "sex":"female" },
	{ "name":"コブシ", "sex":"female" },
	{ "name":"コマクサ", "sex":"female" },
	{ "name":"サクラ", "sex":"female" },
	{ "name":"サクラソウ", "sex":"female" },
	{ "name":"サザンカ", "sex":"female" },
	{ "name":"サツキ", "sex":"female" },
	{ "name":"サルスベリ", "sex":"female" },
	{ "name":"サルビア", "sex":"female" },
	{ "name":"ザゼンソウ", "sex":"female" },
	{ "name":"シクラメン", "sex":"female" },
	{ "name":"シコンノボタン", "sex":"female" },
	{ "name":"シャクナゲ", "sex":"female" },
	{ "name":"シャクヤク", "sex":"female" },
	{ "name":"シュウメイギク", "sex":"female" },
	{ "name":"シラユリ", "sex":"female" },
	{ "name":"シラン", "sex":"female" },
	{ "name":"シロツメクサ", "sex":"female" },
	{ "name":"シンビジウム", "sex":"female" },
	{ "name":"ジャスミン", "sex":"female" },
	{ "name":"ジンチョウゲ", "sex":"female" },
	{ "name":"スイセン", "sex":"female" },
	{ "name":"スイレン", "sex":"female" },
	{ "name":"スズラン", "sex":"female" },
	{ "name":"スダチ", "sex":"female" },
	{ "name":"スノーフレーク", "sex":"female" },
	{ "name":"スミレ", "sex":"female" },
	{ "name":"セイヨウタンポポ", "sex":"female" },
	{ "name":"ゼラニウム", "sex":"female" },
	{ "name":"ソメイヨシノ", "sex":"female" },
	{ "name":"タンポポ", "sex":"female" },
	{ "name":"ダリア", "sex":"female" },
	{ "name":"チゴユリ", "sex":"female" },
	{ "name":"チシマザクラ", "sex":"female" },
	{ "name":"チューリップ", "sex":"female" },
	{ "name":"ツツジ", "sex":"female" },
	{ "name":"ツバキ", "sex":"female" },
	{ "name":"ツユクサ", "sex":"female" },
	{ "name":"デイジー", "sex":"female" },
	{ "name":"トマト", "sex":"female" },
	{ "name":"トリカブト", "sex":"female" },
	{ "name":"ナシ", "sex":"female" },
	{ "name":"ナス", "sex":"female" },
	{ "name":"ナズナ", "sex":"female" },
	{ "name":"ナデシコ", "sex":"female" },
	{ "name":"ニッコウキスゲ", "sex":"female" },
	{ "name":"ニラ", "sex":"female" },
	{ "name":"ニンニク", "sex":"female" },
	{ "name":"ネギ", "sex":"female" },
	{ "name":"ネジバナ", "sex":"female" },
	{ "name":"ネムノキ", "sex":"female" },
	{ "name":"ネモトシャクナゲ", "sex":"female" },
	{ "name":"ノアザミ", "sex":"female" },
	{ "name":"ノバラ", "sex":"female" },
	{ "name":"ハイビスカス", "sex":"female" },
	{ "name":"ハギ", "sex":"female" },
	{ "name":"ハクモクレン", "sex":"female" },
	{ "name":"ハコベ", "sex":"female" },
	{ "name":"ハス", "sex":"female" },
	{ "name":"ハナショウブ", "sex":"female" },
	{ "name":"ハナズオウ", "sex":"female" },
	{ "name":"ハナニラ", "sex":"female" },
	{ "name":"ハナミズキ", "sex":"female" },
	{ "name":"ハバネロ", "sex":"female" },
	{ "name":"ハマギク", "sex":"female" },
	{ "name":"ハマナス", "sex":"female" },
	{ "name":"ハルジオン", "sex":"female" },
	{ "name":"ハーデンベルギア", "sex":"female" },
	{ "name":"バウヒニア", "sex":"female" },
	{ "name":"バジル", "sex":"female" },
	{ "name":"バラ", "sex":"female" },
	{ "name":"パキラ", "sex":"female" },
	{ "name":"パパイヤ", "sex":"female" },
	{ "name":"パンジー", "sex":"female" },
	{ "name":"ヒアシンス", "sex":"female" },
	{ "name":"ヒガンバナ", "sex":"female" },
	{ "name":"ヒナゲシ", "sex":"female" },
	{ "name":"ヒマワリ", "sex":"female" },
	{ "name":"ヒメアヤメ", "sex":"female" },
	{ "name":"ヒメオドリコソウ", "sex":"female" },
	{ "name":"ヒメジョオン", "sex":"female" },
	{ "name":"ヒヤシンス", "sex":"female" },
	{ "name":"ヒルガオ", "sex":"female" },
	{ "name":"ビオラ", "sex":"female" },
	{ "name":"ピーマン", "sex":"female" },
	{ "name":"フウセンカズラ", "sex":"female" },
	{ "name":"フェイジョア", "sex":"female" },
	{ "name":"フキ", "sex":"female" },
	{ "name":"フクジュソウ", "sex":"female" },
	{ "name":"フジ", "sex":"female" },
	{ "name":"フヨウ", "sex":"female" },
	{ "name":"フリージア", "sex":"female" },
	{ "name":"ブッソウゲ", "sex":"female" },
	{ "name":"ブラックキャット", "sex":"female" },
	{ "name":"ブラックベリー", "sex":"female" },
	{ "name":"ブルグマンシア", "sex":"female" },
	{ "name":"ブーゲンビリア", "sex":"female" },
	{ "name":"ヘレボラス", "sex":"female" },
	{ "name":"ベゴニア", "sex":"female" },
	{ "name":"ベニバナ", "sex":"female" },
	{ "name":"ベロニカ", "sex":"female" },
	{ "name":"ペパーミント", "sex":"female" },
	{ "name":"ホウセンカ", "sex":"female" },
	{ "name":"ホオズキ", "sex":"female" },
	{ "name":"ホテイアオイ", "sex":"female" },
	{ "name":"ホトケノザ", "sex":"female" },
	{ "name":"ホトトギス", "sex":"female" },
	{ "name":"ボケ", "sex":"female" },
	{ "name":"ボタン", "sex":"female" },
	{ "name":"ボロニア", "sex":"female" },
	{ "name":"ポインセチア", "sex":"female" },
	{ "name":"ポピー", "sex":"female" },
	{ "name":"マツバボタン", "sex":"female" },
	{ "name":"マリーゴールド", "sex":"female" },
	{ "name":"マンジュシャゲ", "sex":"female" },
	{ "name":"マーガレット", "sex":"female" },
	{ "name":"ミカン", "sex":"female" },
	{ "name":"ミズバショウ", "sex":"female" },
	{ "name":"ミヤギノハギ", "sex":"female" },
	{ "name":"ミヤマキリシマ", "sex":"female" },
	{ "name":"ムクゲ", "sex":"female" },
	{ "name":"ムラサキケマン", "sex":"female" },
	{ "name":"ムラサキサギゴケ", "sex":"female" },
	{ "name":"ムラサキツユクサ", "sex":"female" },
	{ "name":"モウセンゴケ", "sex":"female" },
	{ "name":"モクレン", "sex":"female" },
	{ "name":"モモ", "sex":"female" },
	{ "name":"ヤエザクラ", "sex":"female" },
	{ "name":"ヤグルマギク", "sex":"female" },
	{ "name":"ヤシオツツジ", "sex":"female" },
	{ "name":"ヤナギタンポポ", "sex":"female" },
	{ "name":"ヤマブキ", "sex":"female" },
	{ "name":"ヤマユリ", "sex":"female" },
	{ "name":"ユウガオ", "sex":"female" },
	{ "name":"ユキノシタ", "sex":"female" },
	{ "name":"ユキヤナギ", "sex":"female" },
	{ "name":"ユリ", "sex":"female" },
	{ "name":"ヨルガオ", "sex":"female" },
	{ "name":"ライラック", "sex":"female" },
	{ "name":"ラフレシア", "sex":"female" },
	{ "name":"ラベンダー", "sex":"female" },
	{ "name":"ラン", "sex":"female" },
	{ "name":"リラ", "sex":"female" },
	{ "name":"リリー", "sex":"female" },
	{ "name":"リンゴ", "sex":"female" },
	{ "name":"リンドウ", "sex":"female" },
	{ "name":"ルドベキア", "sex":"female" },
	{ "name":"ルピナス", "sex":"female" },
	{ "name":"ルリムスカリ", "sex":"female" },
	{ "name":"レンゲソウ", "sex":"female" },
	{ "name":"レンゲツツジ", "sex":"female" },
	{ "name":"ワレモコウ", "sex":"female" },

	{ "name":"アイオライト", "sex":"female" },
	{ "name":"アクアマリン", "sex":"female" },
	{ "name":"アゲット", "sex":"female" },
	{ "name":"アズライト", "sex":"female" },
	{ "name":"アパタイト", "sex":"female" },
	{ "name":"アマゾナイト", "sex":"female" },
	{ "name":"アメシスト", "sex":"female" },
	{ "name":"アルマンディン", "sex":"female" },
	{ "name":"アンダルサイト", "sex":"female" },
	{ "name":"アンドラダイト", "sex":"female" },
	{ "name":"アンバー", "sex":"female" },
	{ "name":"ウバロバイト", "sex":"female" },
	{ "name":"ウレキサイト", "sex":"female" },
	{ "name":"エメラルド", "sex":"female" },
	{ "name":"オパール", "sex":"female" },
	{ "name":"オブシディアン", "sex":"female" },
	{ "name":"カイヤナイト", "sex":"female" },
	{ "name":"カルサイト", "sex":"female" },
	{ "name":"カルセドニー", "sex":"female" },
	{ "name":"カーネリアン", "sex":"female" },
	{ "name":"ガーネット", "sex":"female" },
	{ "name":"クリスタル", "sex":"female" },
	{ "name":"クリソコラ", "sex":"female" },
	{ "name":"クリソプレーズ", "sex":"female" },
	{ "name":"クリソベリル", "sex":"female" },
	{ "name":"グロッシュラー", "sex":"female" },
	{ "name":"コランダム", "sex":"female" },
	{ "name":"コーラル", "sex":"female" },
	{ "name":"サファイア", "sex":"female" },
	{ "name":"サンストーン", "sex":"female" },
	{ "name":"サーペンティン", "sex":"female" },
	{ "name":"シェル", "sex":"female" },
	{ "name":"シトリン", "sex":"female" },
	{ "name":"シリマナイト", "sex":"female" },
	{ "name":"ジェダイト", "sex":"female" },
	{ "name":"ジェット", "sex":"female" },
	{ "name":"ジェード", "sex":"female" },
	{ "name":"ジャスパー", "sex":"female" },
	{ "name":"ジルコン", "sex":"female" },
	{ "name":"スギライト", "sex":"female" },
	{ "name":"スピネル", "sex":"female" },
	{ "name":"スフェーン", "sex":"female" },
	{ "name":"スペッサルティン", "sex":"female" },
	{ "name":"スポジュメン", "sex":"female" },
	{ "name":"スミソナイト", "sex":"female" },
	{ "name":"セレスタイト", "sex":"female" },
	{ "name":"ソーダライト", "sex":"female" },
	{ "name":"タイガーズアイ", "sex":"female" },
	{ "name":"タンザナイト", "sex":"female" },
	{ "name":"ターコイズ", "sex":"female" },
	{ "name":"ダイオプサイド", "sex":"female" },
	{ "name":"ダイオプテーズ", "sex":"female" },
	{ "name":"ダイヤモンド", "sex":"female" },
	{ "name":"チューライト", "sex":"female" },
	{ "name":"トパーズ", "sex":"female" },
	{ "name":"トルマリン", "sex":"female" },
	{ "name":"ネフライト", "sex":"female" },
	{ "name":"ハックマナイト", "sex":"female" },
	{ "name":"パイライト", "sex":"female" },
	{ "name":"パイロープ", "sex":"female" },
	{ "name":"パール", "sex":"female" },
	{ "name":"フローライト", "sex":"female" },
	{ "name":"ブラックオパール", "sex":"female" },
	{ "name":"ブラッドストーン", "sex":"female" },
	{ "name":"プレーナイト", "sex":"female" },
	{ "name":"ヘマタイト", "sex":"female" },
	{ "name":"ベスビアナイト", "sex":"female" },
	{ "name":"ベリル", "sex":"female" },
	{ "name":"マラカイト", "sex":"female" },
	{ "name":"ムーンストーン", "sex":"female" },
	{ "name":"ラピスラズリ", "sex":"female" },
	{ "name":"ラピスラズリ", "sex":"female" },
	{ "name":"ラブラドライト", "sex":"female" },
	{ "name":"ルチル", "sex":"female" },
	{ "name":"ルビー", "sex":"female" },
	{ "name":"ローズクォーツ", "sex":"female" },
	{ "name":"ロードクロサイト", "sex":"female" },

	{ "name":"えむい", "sex":"female" },
	{ "name":"ぺけぴ", "sex":"female" },
	{ "name":"にけー", "sex":"female" },

	{ "name":"アオアシシギ", "sex":"male" },
	{ "name":"アオゲラ", "sex":"male" },
	{ "name":"アオサギ", "sex":"male" },
	{ "name":"アオジ", "sex":"male" },
	{ "name":"アオシギ", "sex":"male" },
	{ "name":"アオバズク", "sex":"male" },
	{ "name":"アオバト", "sex":"male" },
	{ "name":"アカアシアジサシ", "sex":"male" },
	{ "name":"アカアシシギ", "sex":"male" },
	{ "name":"アカウソ", "sex":"male" },
	{ "name":"アカガシラサギ", "sex":"male" },
	{ "name":"アカゲラ", "sex":"male" },
	{ "name":"アカコッコ", "sex":"male" },
	{ "name":"アカショウビン", "sex":"male" },
	{ "name":"アカツクシガモ", "sex":"male" },
	{ "name":"アカハシハジロ", "sex":"male" },
	{ "name":"アカハジロ", "sex":"male" },
	{ "name":"アカハラ", "sex":"male" },
	{ "name":"アカハラダカ", "sex":"male" },
	{ "name":"アカハラツバメ", "sex":"male" },
	{ "name":"アカヒゲ", "sex":"male" },
	{ "name":"アカマシコ", "sex":"male" },
	{ "name":"アカモズ", "sex":"male" },
	{ "name":"アカヤマドリ", "sex":"male" },
	{ "name":"アジサシ", "sex":"male" },
	{ "name":"アシナガシギ", "sex":"male" },
	{ "name":"アトリ", "sex":"male" },
	{ "name":"アナドリ", "sex":"male" },
	{ "name":"アネハヅル", "sex":"male" },
	{ "name":"アビ", "sex":"male" },
	{ "name":"アヒル", "sex":"male" },
	{ "name":"アホウドリ", "sex":"male" },
	{ "name":"アマサギ", "sex":"male" },
	{ "name":"アマツバメ", "sex":"male" },
	{ "name":"アマミコゲラ", "sex":"male" },
	{ "name":"アマミヒヨドリ", "sex":"male" },
	{ "name":"アマミヤマガラ", "sex":"male" },
	{ "name":"アマミヤマシギ", "sex":"male" },
	{ "name":"アメリカオシ", "sex":"male" },
	{ "name":"アメリカコガモ", "sex":"male" },
	{ "name":"アメリカヒドリ", "sex":"male" },
	{ "name":"アラナミキンクロ", "sex":"male" },
	{ "name":"アリスイ", "sex":"male" },
	{ "name":"イイジマムシクイ", "sex":"male" },
	{ "name":"イエスズメ", "sex":"male" },
	{ "name":"イオウトウメジロ", "sex":"male" },
	{ "name":"イカル", "sex":"male" },
	{ "name":"イカルチドリ", "sex":"male" },
	{ "name":"イシガキヒヨドリ", "sex":"male" },
	{ "name":"イスカ", "sex":"male" },
	{ "name":"イソシギ", "sex":"male" },
	{ "name":"イソヒヨドリ", "sex":"male" },
	{ "name":"イナバヒタキ", "sex":"male" },
	{ "name":"イヌワシ", "sex":"male" },
	{ "name":"イワツバメ", "sex":"male" },
	{ "name":"イワヒバリ", "sex":"male" },
	{ "name":"イワミセキレイ", "sex":"male" },
	{ "name":"インドガン", "sex":"male" },
	{ "name":"インドクジャク", "sex":"male" },
	{ "name":"インドハッカ", "sex":"male" },
	{ "name":"ウグイス", "sex":"male" },
	{ "name":"ウスアカヒゲ", "sex":"male" },
	{ "name":"ウスアカヤマドリ", "sex":"male" },
	{ "name":"ウズラ", "sex":"male" },
	{ "name":"ウズラシギ", "sex":"male" },
	{ "name":"ウスリームシクイ", "sex":"male" },
	{ "name":"ウソ", "sex":"male" },
	{ "name":"ウトウ", "sex":"male" },
	{ "name":"ウミアイサ", "sex":"male" },
	{ "name":"ウミウ", "sex":"male" },
	{ "name":"ウミオウム", "sex":"male" },
	{ "name":"ウミガラス", "sex":"male" },
	{ "name":"ウミスズメ", "sex":"male" },
	{ "name":"ウミネコ", "sex":"male" },
	{ "name":"ウミバト", "sex":"male" },
	{ "name":"エゾアカゲラ", "sex":"male" },
	{ "name":"エゾオオアカゲラ", "sex":"male" },
	{ "name":"エゾカヤクグリ", "sex":"male" },
	{ "name":"エゾコゲラ", "sex":"male" },
	{ "name":"エゾセンニュウ", "sex":"male" },
	{ "name":"エゾビタキ", "sex":"male" },
	{ "name":"エゾフクロウ", "sex":"male" },
	{ "name":"エゾムシクイ", "sex":"male" },
	{ "name":"エゾヤマセミ", "sex":"male" },
	{ "name":"エゾライチョウ", "sex":"male" },
	{ "name":"エトピリカ", "sex":"male" },
	{ "name":"エナガ", "sex":"male" },
	{ "name":"エリグロアジサシ", "sex":"male" },
	{ "name":"エリマキシギ", "sex":"male" },
	{ "name":"オウゴンチョウ", "sex":"male" },
	{ "name":"オウチュウ", "sex":"male" },
	{ "name":"オオアカゲラ", "sex":"male" },
	{ "name":"オオアカハラ", "sex":"male" },
	{ "name":"オオアジサシ", "sex":"male" },
	{ "name":"オオカラモズ", "sex":"male" },
	{ "name":"オオカワアイサ", "sex":"male" },
	{ "name":"オオカワラヒワ", "sex":"male" },
	{ "name":"オオキアシシギ", "sex":"male" },
	{ "name":"オオクイナ", "sex":"male" },
	{ "name":"オオグンカンドリ", "sex":"male" },
	{ "name":"オオコノハズク", "sex":"male" },
	{ "name":"オオジシギ", "sex":"male" },
	{ "name":"オオジュリン", "sex":"male" },
	{ "name":"オオズグロカモメ", "sex":"male" },
	{ "name":"オオセグロカモメ", "sex":"male" },
	{ "name":"オオセッカ", "sex":"male" },
	{ "name":"オオソリハシシギ", "sex":"male" },
	{ "name":"オオタカ", "sex":"male" },
	{ "name":"オオチドリ", "sex":"male" },
	{ "name":"オオトラツグミ", "sex":"male" },
	{ "name":"オオノスリ", "sex":"male" },
	{ "name":"オオハクチョウ", "sex":"male" },
	{ "name":"オオハシシギ", "sex":"male" },
	{ "name":"オオハム", "sex":"male" },
	{ "name":"オオハヤブサ", "sex":"male" },
	{ "name":"オオバン", "sex":"male" },
	{ "name":"オオヒシクイ", "sex":"male" },
	{ "name":"オオヒバリ", "sex":"male" },
	{ "name":"オオホシハジロ", "sex":"male" },
	{ "name":"オオマガン", "sex":"male" },
	{ "name":"オオマシコ", "sex":"male" },
	{ "name":"オオミズナギドリ", "sex":"male" },
	{ "name":"オオメダイチドリ", "sex":"male" },
	{ "name":"オオモズ", "sex":"male" },
	{ "name":"オオユキホオジロ", "sex":"male" },
	{ "name":"オオヨシキリ", "sex":"male" },
	{ "name":"オオヨシゴイ", "sex":"male" },
	{ "name":"オオルリ", "sex":"male" },
	{ "name":"オオワシ", "sex":"male" },
	{ "name":"オガサワラノスリ", "sex":"male" },
	{ "name":"オガサワラマシコ", "sex":"male" },
	{ "name":"オカヨシガモ", "sex":"male" },
	{ "name":"オガワコマドリ", "sex":"male" },
	{ "name":"オガワミソサザイ", "sex":"male" },
	{ "name":"オグロシギ", "sex":"male" },
	{ "name":"オシドリ", "sex":"male" },
	{ "name":"オジロトウネン", "sex":"male" },
	{ "name":"オジロビタキ", "sex":"male" },
	{ "name":"オジロワシ", "sex":"male" },
	{ "name":"オナガ", "sex":"male" },
	{ "name":"オナガガモ", "sex":"male" },
	{ "name":"オニアジサシ", "sex":"male" },
	{ "name":"オバシギ", "sex":"male" },
	{ "name":"オリイコゲラ", "sex":"male" },
	{ "name":"オリイヤマガラ", "sex":"male" },
	{ "name":"カイツブリ", "sex":"male" },
	{ "name":"カケス", "sex":"male" },
	{ "name":"カゴシマアオゲラ", "sex":"male" },
	{ "name":"カササギ", "sex":"male" },
	{ "name":"カシラダカ", "sex":"male" },
	{ "name":"カタジロワシ", "sex":"male" },
	{ "name":"カツオドリ", "sex":"male" },
	{ "name":"カッコウ", "sex":"male" },
	{ "name":"カナダカモメ", "sex":"male" },
	{ "name":"カナダヅル", "sex":"male" },
	{ "name":"カモメ", "sex":"male" },
	{ "name":"カヤクグリ", "sex":"male" },
	{ "name":"カラアカハラ", "sex":"male" },
	{ "name":"カラシラサギ", "sex":"male" },
	{ "name":"カラスバト", "sex":"male" },
	{ "name":"カラフトウグイス", "sex":"male" },
	{ "name":"カラフトコガラ", "sex":"male" },
	{ "name":"カラフトムシクイ", "sex":"male" },
	{ "name":"カラフトワシ", "sex":"male" },
	{ "name":"カラムクドリ", "sex":"male" },
	{ "name":"カリガネ", "sex":"male" },
	{ "name":"カルガモ", "sex":"male" },
	{ "name":"カワアイサ", "sex":"male" },
	{ "name":"カワウ", "sex":"male" },
	{ "name":"カワガラス", "sex":"male" },
	{ "name":"カワセミ", "sex":"male" },
	{ "name":"カワラヒワ", "sex":"male" },
	{ "name":"カンムリカッコウ", "sex":"male" },
	{ "name":"カンムリワシ", "sex":"male" },
	{ "name":"キアオジ", "sex":"male" },
	{ "name":"キアシシギ", "sex":"male" },
	{ "name":"キガシラシトド", "sex":"male" },
	{ "name":"キガシラセキレイ", "sex":"male" },
	{ "name":"キクイタダキ", "sex":"male" },
	{ "name":"キジ", "sex":"male" },
	{ "name":"キジバト", "sex":"male" },
	{ "name":"キセキレイ", "sex":"male" },
	{ "name":"キタアマツバメ", "sex":"male" },
	{ "name":"キタキバシリ", "sex":"male" },
	{ "name":"キタタキ", "sex":"male" },
	{ "name":"キバシリ", "sex":"male" },
	{ "name":"キビタキ", "sex":"male" },
	{ "name":"キマユホオジロ", "sex":"male" },
	{ "name":"キマユムシクイ", "sex":"male" },
	{ "name":"キュウシュウキジ", "sex":"male" },
	{ "name":"キョウジョシギ", "sex":"male" },
	{ "name":"キョクアジサシ", "sex":"male" },
	{ "name":"キリアイ", "sex":"male" },
	{ "name":"キレンジャク", "sex":"male" },
	{ "name":"キンクロハジロ", "sex":"male" },
	{ "name":"ギンザンマシコ", "sex":"male" },
	{ "name":"キンバト", "sex":"male" },
	{ "name":"ギンムクドリ", "sex":"male" },
	{ "name":"クイナ", "sex":"male" },
	{ "name":"クサシギ", "sex":"male" },
	{ "name":"クビワカモメ", "sex":"male" },
	{ "name":"クビワキンクロ", "sex":"male" },
	{ "name":"クビワコウテンシ", "sex":"male" },
	{ "name":"クマゲラ", "sex":"male" },
	{ "name":"クマタカ", "sex":"male" },
	{ "name":"クロアジサシ", "sex":"male" },
	{ "name":"クロウタドリ", "sex":"male" },
	{ "name":"クロウミツバメ", "sex":"male" },
	{ "name":"クロガモ", "sex":"male" },
	{ "name":"クロサギ", "sex":"male" },
	{ "name":"クロジ", "sex":"male" },
	{ "name":"クロジョウビタキ", "sex":"male" },
	{ "name":"クロツグミ", "sex":"male" },
	{ "name":"クロツラヘラサギ", "sex":"male" },
	{ "name":"クロヅル", "sex":"male" },
	{ "name":"クロトキ", "sex":"male" },
	{ "name":"クロハゲワシ", "sex":"male" },
	{ "name":"クロハラアジサシ", "sex":"male" },
	{ "name":"ケアシノスリ", "sex":"male" },
	{ "name":"ケイマフリ", "sex":"male" },
	{ "name":"ケリ", "sex":"male" },
	{ "name":"ケワタガモ", "sex":"male" },
	{ "name":"コアオアシシギ", "sex":"male" },
	{ "name":"コアカゲラ", "sex":"male" },
	{ "name":"コアジサシ", "sex":"male" },
	{ "name":"コアホウドリ", "sex":"male" },
	{ "name":"コイカル", "sex":"male" },
	{ "name":"ゴイサギ", "sex":"male" },
	{ "name":"コウノトリ", "sex":"male" },
	{ "name":"コウミスズメ", "sex":"male" },
	{ "name":"コウライアイサ", "sex":"male" },
	{ "name":"コウライウグイス", "sex":"male" },
	{ "name":"コウライキジ", "sex":"male" },
	{ "name":"コウライヒクイナ", "sex":"male" },
	{ "name":"コオバシギ", "sex":"male" },
	{ "name":"コオリガモ", "sex":"male" },
	{ "name":"コガモ", "sex":"male" },
	{ "name":"コガラ", "sex":"male" },
	{ "name":"コキアシシギ", "sex":"male" },
	{ "name":"コクガン", "sex":"male" },
	{ "name":"コクチョウ", "sex":"male" },
	{ "name":"コクマルガラス", "sex":"male" },
	{ "name":"コグンカンドリ", "sex":"male" },
	{ "name":"コゲラ", "sex":"male" },
	{ "name":"コケワタガモ", "sex":"male" },
	{ "name":"コサギ", "sex":"male" },
	{ "name":"コサメビタキ", "sex":"male" },
	{ "name":"コシアカツバメ", "sex":"male" },
	{ "name":"コシギ", "sex":"male" },
	{ "name":"コシジロアジサシ", "sex":"male" },
	{ "name":"コシジロヤマドリ", "sex":"male" },
	{ "name":"コシャクシギ", "sex":"male" },
	{ "name":"ゴジュウカラ", "sex":"male" },
	{ "name":"コジュケイ", "sex":"male" },
	{ "name":"コジュリン", "sex":"male" },
	{ "name":"コスズガモ", "sex":"male" },
	{ "name":"コチドリ", "sex":"male" },
	{ "name":"コチョウゲンボウ", "sex":"male" },
	{ "name":"コトラツグミ", "sex":"male" },
	{ "name":"コノハズク", "sex":"male" },
	{ "name":"コハクチョウ", "sex":"male" },
	{ "name":"コバシチドリ", "sex":"male" },
	{ "name":"ゴビズキンカモメ", "sex":"male" },
	{ "name":"コヒバリ", "sex":"male" },
	{ "name":"コブハクチョウ", "sex":"male" },
	{ "name":"コベニヒワ", "sex":"male" },
	{ "name":"コホオアカ", "sex":"male" },
	{ "name":"コマドリ", "sex":"male" },
	{ "name":"ゴマフスズメ", "sex":"male" },
	{ "name":"コミズナギドリ", "sex":"male" },
	{ "name":"コミミズク", "sex":"male" },
	{ "name":"コムクドリ", "sex":"male" },
	{ "name":"コメボソムシクイ", "sex":"male" },
	{ "name":"コモンシギ", "sex":"male" },
	{ "name":"コヨシキリ", "sex":"male" },
	{ "name":"コルリ", "sex":"male" },
	{ "name":"サカツラガン", "sex":"male" },
	{ "name":"サケイ", "sex":"male" },
	{ "name":"ササゴイ", "sex":"male" },
	{ "name":"サシバ", "sex":"male" },
	{ "name":"サバクヒタキ", "sex":"male" },
	{ "name":"サメビタキ", "sex":"male" },
	{ "name":"サルハマシギ", "sex":"male" },
	{ "name":"サンカノゴイ", "sex":"male" },
	{ "name":"サンコウチョウ", "sex":"male" },
	{ "name":"サンショウクイ", "sex":"male" },
	{ "name":"シコクコゲラ", "sex":"male" },
	{ "name":"シコクヤマドリ", "sex":"male" },
	{ "name":"シジュウカラ", "sex":"male" },
	{ "name":"シジュウカラガン", "sex":"male" },
	{ "name":"シチトウメジロ", "sex":"male" },
	{ "name":"シナガチョウ", "sex":"male" },
	{ "name":"シノリガモ", "sex":"male" },
	{ "name":"シベリアアオジ", "sex":"male" },
	{ "name":"シベリアアリスイ", "sex":"male" },
	{ "name":"シベリアオオモズ", "sex":"male" },
	{ "name":"シベリアシメ", "sex":"male" },
	{ "name":"シベリアジュリン", "sex":"male" },
	{ "name":"シベリアハヤブサ", "sex":"male" },
	{ "name":"シベリアムクドリ", "sex":"male" },
	{ "name":"シマアオジ", "sex":"male" },
	{ "name":"シマアカモズ", "sex":"male" },
	{ "name":"シマアジ", "sex":"male" },
	{ "name":"シマエナガ", "sex":"male" },
	{ "name":"シマキジ", "sex":"male" },
	{ "name":"シマキンパラ", "sex":"male" },
	{ "name":"シマクイナ", "sex":"male" },
	{ "name":"シマゴマ", "sex":"male" },
	{ "name":"シマセンニュウ", "sex":"male" },
	{ "name":"シマノジコ", "sex":"male" },
	{ "name":"シマハヤブサ", "sex":"male" },
	{ "name":"シマフクロウ", "sex":"male" },
	{ "name":"シマメジロ", "sex":"male" },
	{ "name":"シメ", "sex":"male" },
	{ "name":"ジュウイチ", "sex":"male" },
	{ "name":"ショウドウツバメ", "sex":"male" },
	{ "name":"ジョウビタキ", "sex":"male" },
	{ "name":"シラガホオジロ", "sex":"male" },
	{ "name":"シラコバト", "sex":"male" },
	{ "name":"シロアジサシ", "sex":"male" },
	{ "name":"シロエリオオハム", "sex":"male" },
	{ "name":"シロガシラ", "sex":"male" },
	{ "name":"シロカモメ", "sex":"male" },
	{ "name":"シロチドリ", "sex":"male" },
	{ "name":"シロハヤブサ", "sex":"male" },
	{ "name":"シロハラ", "sex":"male" },
	{ "name":"シロハラクイナ", "sex":"male" },
	{ "name":"シロハラホオジロ", "sex":"male" },
	{ "name":"シロフクロウ", "sex":"male" },
	{ "name":"ズアオアトリ", "sex":"male" },
	{ "name":"ズアオホオジロ", "sex":"male" },
	{ "name":"ズアカアオバト", "sex":"male" },
	{ "name":"ズグロカモメ", "sex":"male" },
	{ "name":"ズグロミゾゴイ", "sex":"male" },
	{ "name":"スズガモ", "sex":"male" },
	{ "name":"スズメ", "sex":"male" },
	{ "name":"セイタカシギ", "sex":"male" },
	{ "name":"セグロアジサシ", "sex":"male" },
	{ "name":"セグロカッコウ", "sex":"male" },
	{ "name":"セグロカモメ", "sex":"male" },
	{ "name":"セグロセキレイ", "sex":"male" },
	{ "name":"セジロタヒバリ", "sex":"male" },
	{ "name":"セッカ", "sex":"male" },
	{ "name":"センダイムシクイ", "sex":"male" },
	{ "name":"ゾウゲカモメ", "sex":"male" },
	{ "name":"ソデグロヅル", "sex":"male" },
	{ "name":"ソリハシシギ", "sex":"male" },
	{ "name":"ダイサギ", "sex":"male" },
	{ "name":"ダイシャクシギ", "sex":"male" },
	{ "name":"ダイゼン", "sex":"male" },
	{ "name":"ダイトウウグイス", "sex":"male" },
	{ "name":"ダイトウノスリ", "sex":"male" },
	{ "name":"ダイトウヒヨドリ", "sex":"male" },
	{ "name":"ダイトウメジロ", "sex":"male" },
	{ "name":"ダイトウヤマガラ", "sex":"male" },
	{ "name":"タイワンヒヨドリ", "sex":"male" },
	{ "name":"タカサゴクロサギ", "sex":"male" },
	{ "name":"タカサゴモズ", "sex":"male" },
	{ "name":"タカブシギ", "sex":"male" },
	{ "name":"タゲリ", "sex":"male" },
	{ "name":"タシギ", "sex":"male" },
	{ "name":"タネアオゲラ", "sex":"male" },
	{ "name":"タネコマドリ", "sex":"male" },
	{ "name":"タネヤマガラ", "sex":"male" },
	{ "name":"タヒバリ", "sex":"male" },
	{ "name":"タマシギ", "sex":"male" },
	{ "name":"タンチョウ", "sex":"male" },
	{ "name":"チゴハヤブサ", "sex":"male" },
	{ "name":"チゴモズ", "sex":"male" },
	{ "name":"チシマウガラス", "sex":"male" },
	{ "name":"チシマシギ", "sex":"male" },
	{ "name":"チャキンチョウ", "sex":"male" },
	{ "name":"チュウサギ", "sex":"male" },
	{ "name":"チュウジシギ", "sex":"male" },
	{ "name":"チュウシャクシギ", "sex":"male" },
	{ "name":"チュウダイサギ", "sex":"male" },
	{ "name":"チュウヒ", "sex":"male" },
	{ "name":"チョウゲンボウ", "sex":"male" },
	{ "name":"チョウセンエナガ", "sex":"male" },
	{ "name":"ツクシガモ", "sex":"male" },
	{ "name":"ツグミ", "sex":"male" },
	{ "name":"ツシマコゲラ", "sex":"male" },
	{ "name":"ツツドリ", "sex":"male" },
	{ "name":"ツノメドリ", "sex":"male" },
	{ "name":"ツバメ", "sex":"male" },
	{ "name":"ツバメチドリ", "sex":"male" },
	{ "name":"ツミ", "sex":"male" },
	{ "name":"ツメナガセキレイ", "sex":"male" },
	{ "name":"ツメナガホオジロ", "sex":"male" },
	{ "name":"ツリスガラ", "sex":"male" },
	{ "name":"ツルクイナ", "sex":"male" },
	{ "name":"ツルシギ", "sex":"male" },
	{ "name":"トウカイキジ", "sex":"male" },
	{ "name":"トウゾクカモメ", "sex":"male" },
	{ "name":"トウネン", "sex":"male" },
	{ "name":"トキ", "sex":"male" },
	{ "name":"ドバト", "sex":"male" },
	{ "name":"トビ", "sex":"male" },
	{ "name":"トモエガモ", "sex":"male" },
	{ "name":"トラツグミ", "sex":"male" },
	{ "name":"トラフズク", "sex":"male" },
	{ "name":"ナキイスカ", "sex":"male" },
	{ "name":"ナキハクチョウ", "sex":"male" },
	{ "name":"ナベコウ", "sex":"male" },
	{ "name":"ナベヅル", "sex":"male" },
	{ "name":"ナミエヤマガラ", "sex":"male" },
	{ "name":"ニュウナイスズメ", "sex":"male" },
	{ "name":"ノガン", "sex":"male" },
	{ "name":"ノグチゲラ", "sex":"male" },
	{ "name":"ノゴマ", "sex":"male" },
	{ "name":"ノジコ", "sex":"male" },
	{ "name":"ノスリ", "sex":"male" },
	{ "name":"ノドグロツグミ", "sex":"male" },
	{ "name":"ノハラツグミ", "sex":"male" },
	{ "name":"ノビタキ", "sex":"male" },
	{ "name":"ハイイロアジサシ", "sex":"male" },
	{ "name":"ハイイロガン", "sex":"male" },
	{ "name":"ハイイロチュウヒ", "sex":"male" },
	{ "name":"ハイイロペリカン", "sex":"male" },
	{ "name":"ハイタカ", "sex":"male" },
	{ "name":"ハギマシコ", "sex":"male" },
	{ "name":"ハクガン", "sex":"male" },
	{ "name":"ハクセキレイ", "sex":"male" },
	{ "name":"ハシグロヒタキ", "sex":"male" },
	{ "name":"ハシジロアビ", "sex":"male" },
	{ "name":"ハシナガウグイス", "sex":"male" },
	{ "name":"ハシビロガモ", "sex":"male" },
	{ "name":"ハシブトアカゲラ", "sex":"male" },
	{ "name":"ハシブトアジサシ", "sex":"male" },
	{ "name":"ハシブトガラ", "sex":"male" },
	{ "name":"ハシブトガラス", "sex":"male" },
	{ "name":"ハシブトゴイ", "sex":"male" },
	{ "name":"ハシブトヒヨドリ", "sex":"male" },
	{ "name":"ハシボソカモメ", "sex":"male" },
	{ "name":"ハシボソガラス", "sex":"male" },
	{ "name":"ハジロカイツブリ", "sex":"male" },
	{ "name":"ハジロコチドリ", "sex":"male" },
	{ "name":"ハチクイ", "sex":"male" },
	{ "name":"ハチクマ", "sex":"male" },
	{ "name":"ハチジョウツグミ", "sex":"male" },
	{ "name":"ハハジマメグロ", "sex":"male" },
	{ "name":"ハマシギ", "sex":"male" },
	{ "name":"ハマヒバリ", "sex":"male" },
	{ "name":"ハヤブサ", "sex":"male" },
	{ "name":"ハリオアマツバメ", "sex":"male" },
	{ "name":"ハリオシギ", "sex":"male" },
	{ "name":"バリケン", "sex":"male" },
	{ "name":"バン", "sex":"male" },
	{ "name":"ヒガラ", "sex":"male" },
	{ "name":"ヒクイナ", "sex":"male" },
	{ "name":"ヒゲガラ", "sex":"male" },
	{ "name":"ヒシクイ", "sex":"male" },
	{ "name":"ヒドリガモ", "sex":"male" },
	{ "name":"ヒバリ", "sex":"male" },
	{ "name":"ヒバリシギ", "sex":"male" },
	{ "name":"ヒメアマツバメ", "sex":"male" },
	{ "name":"ヒメウ", "sex":"male" },
	{ "name":"ヒメウズラシギ", "sex":"male" },
	{ "name":"ヒメクイナ", "sex":"male" },
	{ "name":"ヒメクビワカモメ", "sex":"male" },
	{ "name":"ヒメクロアジサシ", "sex":"male" },
	{ "name":"ヒメコウテンシ", "sex":"male" },
	{ "name":"ヒメノガン", "sex":"male" },
	{ "name":"ヒメハジロ", "sex":"male" },
	{ "name":"ヒメハマシギ", "sex":"male" },
	{ "name":"ヒメヒシクイ", "sex":"male" },
	{ "name":"ヒヨドリ", "sex":"male" },
	{ "name":"ヒレンジャク", "sex":"male" },
	{ "name":"ビロードキンクロ", "sex":"male" },
	{ "name":"ビンズイ", "sex":"male" },
	{ "name":"フクロウ", "sex":"male" },
	{ "name":"ブッポウソウ", "sex":"male" },
	{ "name":"フルマカモメ", "sex":"male" },
	{ "name":"ベニアジサシ", "sex":"male" },
	{ "name":"ベニバト", "sex":"male" },
	{ "name":"ベニバラウソ", "sex":"male" },
	{ "name":"ベニヒワ", "sex":"male" },
	{ "name":"ベニマシコ", "sex":"male" },
	{ "name":"ヘラサギ", "sex":"male" },
	{ "name":"ヘラシギ", "sex":"male" },
	{ "name":"ホウロクシギ", "sex":"male" },
	{ "name":"ホオアカ", "sex":"male" },
	{ "name":"ホオジロ", "sex":"male" },
	{ "name":"ホオジロガモ", "sex":"male" },
	{ "name":"ホシガラス", "sex":"male" },
	{ "name":"ホシハジロ", "sex":"male" },
	{ "name":"ホシムクドリ", "sex":"male" },
	{ "name":"ホトトギス", "sex":"male" },
	{ "name":"ホントウアカヒゲ", "sex":"male" },
	{ "name":"マガモ", "sex":"male" },
	{ "name":"マガン", "sex":"male" },
	{ "name":"マキノセンニュウ", "sex":"male" },
	{ "name":"マダラウミスズメ", "sex":"male" },
	{ "name":"マダラチュウヒ", "sex":"male" },
	{ "name":"マダラヒタキ", "sex":"male" },
	{ "name":"マナヅル", "sex":"male" },
	{ "name":"マヒワ", "sex":"male" },
	{ "name":"マミジロ", "sex":"male" },
	{ "name":"マミジロアジサシ", "sex":"male" },
	{ "name":"マミジロキビタキ", "sex":"male" },
	{ "name":"マミジロクイナ", "sex":"male" },
	{ "name":"マミジロタヒバリ", "sex":"male" },
	{ "name":"マミチャジナイ", "sex":"male" },
	{ "name":"マリアナヨシゴイ", "sex":"male" },
	{ "name":"ミカドガン", "sex":"male" },
	{ "name":"ミコアイサ", "sex":"male" },
	{ "name":"ミサゴ", "sex":"male" },
	{ "name":"ミゾゴイ", "sex":"male" },
	{ "name":"ミソサザイ", "sex":"male" },
	{ "name":"ミツユビカモメ", "sex":"male" },
	{ "name":"ミドリツバメ", "sex":"male" },
	{ "name":"ミフウズラ", "sex":"male" },
	{ "name":"ミミカイツブリ", "sex":"male" },
	{ "name":"ミヤケコゲラ", "sex":"male" },
	{ "name":"ミヤコショウビン", "sex":"male" },
	{ "name":"ミヤコドリ", "sex":"male" },
	{ "name":"ミヤマカケス", "sex":"male" },
	{ "name":"ミヤマガラス", "sex":"male" },
	{ "name":"ミヤマシトド", "sex":"male" },
	{ "name":"ミヤマホオジロ", "sex":"male" },
	{ "name":"ミユビゲラ", "sex":"male" },
	{ "name":"ミユビシギ", "sex":"male" },
	{ "name":"ムギマキ", "sex":"male" },
	{ "name":"ムクドリ", "sex":"male" },
	{ "name":"ムコジマメグロ", "sex":"male" },
	{ "name":"ムジセッカ", "sex":"male" },
	{ "name":"ムナグロ", "sex":"male" },
	{ "name":"ムネアカタヒバリ", "sex":"male" },
	{ "name":"ムラサキサギ", "sex":"male" },
	{ "name":"メジロ", "sex":"male" },
	{ "name":"メジロガモ", "sex":"male" },
	{ "name":"メダイチドリ", "sex":"male" },
	{ "name":"メボソムシクイ", "sex":"male" },
	{ "name":"モズ", "sex":"male" },
	{ "name":"モスケミソサザイ", "sex":"male" },
	{ "name":"モミヤマフクロウ", "sex":"male" },
	{ "name":"モモイロペリカン", "sex":"male" },
	{ "name":"モリツバメ", "sex":"male" },
	{ "name":"モリムシクイ", "sex":"male" },
	{ "name":"モンゴルカモメ", "sex":"male" },
	{ "name":"ヤイロチョウ", "sex":"male" },
	{ "name":"ヤクシマカケス", "sex":"male" },
	{ "name":"ヤクシマヤマガラ", "sex":"male" },
	{ "name":"ヤツガシラ", "sex":"male" },
	{ "name":"ヤブサメ", "sex":"male" },
	{ "name":"ヤマガラ", "sex":"male" },
	{ "name":"ヤマゲラ", "sex":"male" },
	{ "name":"ヤマザキヒタキ", "sex":"male" },
	{ "name":"ヤマシギ", "sex":"male" },
	{ "name":"ヤマショウビン", "sex":"male" },
	{ "name":"ヤマセミ", "sex":"male" },
	{ "name":"ヤマドリ", "sex":"male" },
	{ "name":"ヤマヒバリ", "sex":"male" },
	{ "name":"ヤンバルクイナ", "sex":"male" },
	{ "name":"ユキホオジロ", "sex":"male" },
	{ "name":"ユリカモメ", "sex":"male" },
	{ "name":"ヨシガモ", "sex":"male" },
	{ "name":"ヨシゴイ", "sex":"male" },
	{ "name":"ヨタカ", "sex":"male" },
	{ "name":"ライチョウ", "sex":"male" },
	{ "name":"リュウキュウガモ", "sex":"male" },
	{ "name":"リュウキュウツミ", "sex":"male" },
	{ "name":"ルリカケス", "sex":"male" },
	{ "name":"ルリガラ", "sex":"male" },
	{ "name":"ルリビタキ", "sex":"male" },
	{ "name":"レンカク", "sex":"male" },
	{ "name":"ワキアカツグミ", "sex":"male" },
	{ "name":"ワシカモメ", "sex":"male" },
	{ "name":"ワシミミズク", "sex":"male" },
	{ "name":"ワタリガラス", "sex":"male" },

	{ "name":"リチウム", "sex":"male" },
	{ "name":"ナトリウム", "sex":"male" },
	{ "name":"カリウム", "sex":"male" },
	{ "name":"ルビジウム", "sex":"male" },
	{ "name":"セシウム", "sex":"male" },
	{ "name":"フランシウム", "sex":"male" },
	{ "name":"ベリリウム", "sex":"male" },
	{ "name":"マグネシウム", "sex":"male" },
	{ "name":"カルシウム", "sex":"male" },
	{ "name":"ストロンチウム", "sex":"male" },
	{ "name":"バリウム", "sex":"male" },
	{ "name":"スカンジウム", "sex":"male" },
	{ "name":"チタン", "sex":"male" },
	{ "name":"バナジウム", "sex":"male" },
	{ "name":"クロム", "sex":"male" },
	{ "name":"マンガン", "sex":"male" },
	{ "name":"アイアン", "sex":"male" },
	{ "name":"コバルト", "sex":"male" },
	{ "name":"ニッケル", "sex":"male" },
	{ "name":"カッパー", "sex":"male" },
	{ "name":"ジンク", "sex":"male" },
	{ "name":"イットリウム", "sex":"male" },
	{ "name":"ジルコニウム", "sex":"male" },
	{ "name":"ニオブ", "sex":"male" },
	{ "name":"モリブデン", "sex":"male" },
	{ "name":"テクネチウム", "sex":"male" },
	{ "name":"ルテニウム", "sex":"male" },
	{ "name":"ロジウム", "sex":"male" },
	{ "name":"パラジウム", "sex":"male" },
	{ "name":"シルバー", "sex":"male" },
	{ "name":"カドミウム", "sex":"male" },
	{ "name":"ランタン", "sex":"male" },
	{ "name":"セリウム", "sex":"male" },
	{ "name":"プラセオジム", "sex":"male" },
	{ "name":"ネオジム", "sex":"male" },
	{ "name":"プロメチウム", "sex":"male" },
	{ "name":"サマリウム", "sex":"male" },
	{ "name":"ユウロピウム", "sex":"male" },
	{ "name":"ガドリニウム", "sex":"male" },
	{ "name":"テルビウム", "sex":"male" },
	{ "name":"ジスプロシウム", "sex":"male" },
	{ "name":"ホルミウム", "sex":"male" },
	{ "name":"エルビウム", "sex":"male" },
	{ "name":"ツリウム", "sex":"male" },
	{ "name":"イッテルビウム", "sex":"male" },
	{ "name":"ルテチウム", "sex":"male" },
	{ "name":"ハフニウム", "sex":"male" },
	{ "name":"タンタル", "sex":"male" },
	{ "name":"タングステン", "sex":"male" },
	{ "name":"レニウム", "sex":"male" },
	{ "name":"オスミウム", "sex":"male" },
	{ "name":"イリジウム", "sex":"male" },
	{ "name":"プラチナ", "sex":"male" },
	{ "name":"ゴールド", "sex":"male" }
]}
